<?xml version="1.0" encoding="UTF-8" ?>
<CLLConfig>
	<GeneralConfiguration></GeneralConfiguration>
	<SpecialConfigurations>
		<!-- This is the configuration for the Ultra Remote Control -->
		<Configuration name ="SomeCommands">
			<Title>Some Commands</Title>
			<LabelText>What do you want to do?</LabelText>
			<GridWidth>3</GridWidth>
			<ShowCommandOutput>1</ShowCommandOutput>
			<CommandList>
				<Command text="Wake Ultra"><![CDATA[sudo etherwake -D 00:1C:85:40:24:E3]]></Command>
				<Command text="Shutdown Ultra"><![CDATA[ssh -v ultra@ultra.local sudo shutdown -h now]]></Command>
				<Command text="Ping Ulta"><![CDATA[ping -c 3 ultra.local]]></Command>
				<Command text="Wake Marenostrum2"><![CDATA[sudo etherwake -D 00:1C:C0:60:F0:6C]]></Command>
				<Command text="Bark"><![CDATA[play /usr/share/sounds/gnome/default/alerts/bark.ogg]]></Command>	
				<Command text="Bark"><![CDATA[play /usr/share/sounds/gnome/default/alerts/bark.ogg]]></Command>	
			</CommandList>
		</Configuration>
		<!-- This is a configuration for Testing -->
		<Configuration name="TestLauncher">
			<Title>Test Configuration</Title>
			<LabelText>This is a Test configuration for CommandLineLauncher\nBlah Blah Blah\n Zack Bumm Peng!</LabelText>
			<GridWidth>3</GridWidth>
			<ShowCommandOutput>1</ShowCommandOutput>
			<CommandList>
				<Command text="Bark1"><![CDATA[play /usr/share/sounds/gnome/default/alerts/bark.ogg]]></Command>	
				<Command text="Drip1"><![CDATA[play /usr/share/sounds/gnome/default/alerts/drip.ogg]]></Command>	
				<Command text="Glass1"><![CDATA[play /usr/share/sounds/gnome/default/alerts/glass.ogg]]></Command>	
				<Command text="Sonar1"><![CDATA[play /usr/share/sounds/gnome/default/alerts/sonar.ogg]]></Command>	
				<Command text="Bark2"><![CDATA[play /usr/share/sounds/gnome/default/alerts/bark.ogg]]></Command>	
				<Command text="Drip2"><![CDATA[play /usr/share/sounds/gnome/default/alerts/drip.ogg]]></Command>	
				<Command text="Glass2"><![CDATA[play /usr/share/sounds/gnome/default/alerts/glass.ogg]]></Command>	
				<Command text="Sonar2"><![CDATA[play /usr/share/sounds/gnome/default/alerts/sonar.ogg]]></Command>	
			</CommandList>
		</Configuration>
	</SpecialConfigurations>
</CLLConfig>
